xwarning/__init__.py
xwarning/__main__.py
xwarning/xwarning.py
xwarning-0.18.dist-info/licenses/LICENSE
xwarning-0.18.dist-info/METADATA
xwarning-0.18.dist-info/WHEEL
xwarning-0.18.dist-info/entry_points.txt
xwarning-0.18.dist-info/top_level.txt
xwarning-0.18.dist-info/RECORD
