Metadata-Version: 2.4
Name: xwarning
Version: 0.18
Summary: Enhanced Python warnings with beautiful, color-coded output with icons and colors.
Home-page: https://github.com/cumulus13/xwarning
Author: Hadi Cahyadi
License: MIT
Classifier: Programming Language :: Python :: 3
Classifier: License :: OSI Approved :: MIT License
Classifier: Operating System :: OS Independent
Requires-Python: >=3.7
License-File: LICENSE
Dynamic: author
Dynamic: classifier
Dynamic: description
Dynamic: description-content-type
Dynamic: home-page
Dynamic: license
Dynamic: license-file
Dynamic: requires-python
Dynamic: summary
